odap/common/config.py
odap/common/databricks.py
odap/common/dataframes.py
odap/common/exceptions.py
odap/common/functions.py
odap/common/logger.py
odap/common/notebook.py
odap/common/tables.py
odap/common/utils.py
odap/common/widgets.py
odap/common/test/PySparkTestCase.py
odap/common/test/runner.py
odap/common/test/notebook/NotebookParsingTest.py
odap/common/test/notebook/python_notebook.txt
odap/common/test/notebook/sql_notebook.txt
odap/feature_factory/config.py
odap/feature_factory/const.py
odap/feature_factory/context.py
odap/feature_factory/dq_checks.py
odap/feature_factory/dry_run.py
odap/feature_factory/exceptions.py
odap/feature_factory/feature_notebook.py
odap/feature_factory/feature_notebooks_selection.py
odap/feature_factory/feature_store.py
odap/feature_factory/feature_store_backfill.py
odap/feature_factory/imports.py
odap/feature_factory/metadata.py
odap/feature_factory/metadata_schema.py
odap/feature_factory/no_target_optimizer.py
odap/feature_factory/orchestrate.py
odap/feature_factory/tables_validator.py
odap/feature_factory/templates.py
odap/feature_factory/time_windows.py
odap/feature_factory/type_checker.py
odap/feature_factory/utils.py
odap/feature_factory/widgets.py
odap/feature_factory/dataframes/dataframe_checker.py
odap/feature_factory/dataframes/dataframe_creator.py
odap/feature_factory/dataframes/dataframe_writer.py
odap/feature_factory/tests/LatestDataFrameTest.py
odap/feature_factory/tests/NoTargetOptimizationTest.py
odap/feature_factory/tests/TimeWindowsTest.py
odap/feature_factory/tests/metadata_test.py
odap/segment_factory/Export.py
odap/segment_factory/config.py
odap/segment_factory/config_checker.py
odap/segment_factory/exceptions.py
odap/segment_factory/exporters.py
odap/segment_factory/logs.py
odap/segment_factory/orchestrate.py
odap/segment_factory/schemas.py
odap/segment_factory/segments.py
odap/segment_factory/use_cases.py
odap/segment_factory/widgets.py
odap/use_case/config.py
odap/use_case/functions.py
odap-0.5.1.dist-info/METADATA
odap-0.5.1.dist-info/WHEEL
odap-0.5.1.dist-info/entry_points.txt
odap-0.5.1.dist-info/licenses/LICENSE
odap-0.5.1.dist-info/RECORD
