Metadata-Version: 2.4
Name: odap
Version: 0.5.1
Summary: ODAP framework
Author-email: Lukas Langr <lukas.langr@datasentics.com>, Karel Gudera <karel.gudera@datasentics.com>
License: LICENSING TERMS
License-File: LICENSE
Requires-Python: ~=3.8
